pickit/__init__.py
pickit/analyze_interactions.py
pickit_urv-1.0.0.dist-info/licenses/LICENSE.txt
pickit_urv-1.0.0.dist-info/METADATA
pickit_urv-1.0.0.dist-info/WHEEL
pickit_urv-1.0.0.dist-info/top_level.txt
pickit_urv-1.0.0.dist-info/RECORD
