Metadata-Version: 2.4
Name: pickit-urv
Version: 1.0.0
Summary: Librería para seleccionar y analizar interacciones moleculares según su actividad de unión (pIC50).
Home-page: https://github.com/31ldts
Author: Said Trujillo de León
Author-email: 31ldts@gmail.com
License: GNU AFFERO GENERAL PUBLIC LICENSE
License-File: LICENSE.txt
Requires-Dist: matplotlib>=3.1.0
Requires-Dist: mplcursors>=0.6
Requires-Dist: pandas>=2.0.0
Requires-Dist: numpy>=2.0.0
Requires-Dist: seaborn>=0.13.2
Requires-Dist: openpyxl>=3.1.5
Dynamic: author
Dynamic: author-email
Dynamic: description
Dynamic: description-content-type
Dynamic: home-page
Dynamic: license
Dynamic: license-file
Dynamic: requires-dist
Dynamic: summary
